{"Alfombras_y_felpudos": [ {"nodes": [{"id": "Los Ángeles", "group": 1, "monto": 8327200, "cantidad": 6},{"id": "Chanco", "group": 1, "monto": 3275437, "cantidad": 1},{"id": "Puerto Montt", "group": 1, "monto": 913899, "cantidad": 6},{"id": "Los Lagos", "group": 1, "monto": 304390, "cantidad": 2},{"id": "Cauquenes", "group": 1, "monto": 669099, "cantidad": 2},{"id": "Vilcún", "group": 1, "monto": 80700, "cantidad": 1},{"id": "Providencia", "group": 1, "monto": 1950000, "cantidad": 1},{"id": "Victoria", "group": 1, "monto": 392589, "cantidad": 2},{"id": "Quillón", "group": 1, "monto": 116038, "cantidad": 1},{"id": "Hualqui", "group": 1, "monto": 188486, "cantidad": 1},{"id": "San Fabián", "group": 1, "monto": 1271444, "cantidad": 2},{"id": "Lebu", "group": 1, "monto": 965425, "cantidad": 3},{"id": "Futaleufú", "group": 1, "monto": 383212, "cantidad": 1},{"id": "Quinchao", "group": 1, "monto": 139221, "cantidad": 1},{"id": "Vallenar", "group": 1, "monto": 2807007, "cantidad": 4},{"id": "Hualaihue", "group": 1, "monto": 2886193, "cantidad": 4},{"id": "Chile Chico", "group": 1, "monto": 159704, "cantidad": 2},{"id": "Palena", "group": 1, "monto": 314984, "cantidad": 1},{"id": "Combarbalá", "group": 1, "monto": 419976, "cantidad": 2},{"id": "Carahue", "group": 1, "monto": 593424, "cantidad": 1},{"id": "Valdivia", "group": 1, "monto": 5547095, "cantidad": 5},{"id": "Los Álamos", "group": 1, "monto": 21267, "cantidad": 1},{"id": "Pichidegua", "group": 1, "monto": 502905, "cantidad": 3},{"id": "San Rafael", "group": 1, "monto": 451089, "cantidad": 3},{"id": "Colbún", "group": 1, "monto": 155380, "cantidad": 1},{"id": "Coltauco", "group": 1, "monto": 435992, "cantidad": 2},{"id": "Coronel", "group": 1, "monto": 1611737, "cantidad": 1},{"id": "Tucapel", "group": 1, "monto": 207076, "cantidad": 1},{"id": "Arauco", "group": 1, "monto": 1545312, "cantidad": 3},{"id": "Paillaco", "group": 1, "monto": 148174, "cantidad": 2},{"id": "San Gregorio", "group": 1, "monto": 428953, "cantidad": 4},{"id": "Los Muermos", "group": 1, "monto": 70511, "cantidad": 1},{"id": "La Ligua", "group": 1, "monto": 3824807, "cantidad": 4},{"id": "Temuco", "group": 1, "monto": 6110417, "cantidad": 3},{"id": "Huechuraba", "group": 1, "monto": 443809, "cantidad": 1},{"id": "Aysén", "group": 1, "monto": 104378, "cantidad": 1},{"id": "Chillán", "group": 1, "monto": 1157418, "cantidad": 2},{"id": "San Rosendo", "group": 1, "monto": 597308, "cantidad": 1},{"id": "Fresia", "group": 1, "monto": 259066, "cantidad": 1},{"id": "La Cisterna", "group": 1, "monto": 453747, "cantidad": 3},{"id": "Pitrufquén", "group": 1, "monto": 241683, "cantidad": 2},{"id": "La Unión", "group": 1, "monto": 352725, "cantidad": 2},{"id": "Diego de Almagro", "group": 1, "monto": 331962, "cantidad": 1},{"id": "Lago Ranco", "group": 1, "monto": 36028, "cantidad": 1},{"id": "Puerto Octay", "group": 1, "monto": 95413, "cantidad": 1},{"id": "San Esteban", "group": 1, "monto": 303821, "cantidad": 1},{"id": "Lumaco", "group": 1, "monto": 431150, "cantidad": 2},{"id": "Calama", "group": 1, "monto": 2630649, "cantidad": 1},{"id": "Traiguén", "group": 1, "monto": 50437, "cantidad": 1},{"id": "Chillán Viejo", "group": 1, "monto": 1040400, "cantidad": 1},{"id": "Lonquimay", "group": 1, "monto": 1033212, "cantidad": 2},{"id": "Florida", "group": 1, "monto": 536100, "cantidad": 1},{"id": "Mulchén", "group": 1, "monto": 1076613, "cantidad": 1},{"id": "San Pablo", "group": 1, "monto": 235154, "cantidad": 1},{"id": "Osorno", "group": 1, "monto": 334483, "cantidad": 2},{"id": "Colchane", "group": 1, "monto": 418820, "cantidad": 2},{"id": "Nacimiento", "group": 1, "monto": 752284, "cantidad": 4},{"id": "Lo Barnechea", "group": 1, "monto": 324834, "cantidad": 2},{"id": "Frutillar", "group": 1, "monto": 344237, "cantidad": 1},{"id": "Río Claro", "group": 1, "monto": 209485, "cantidad": 1},{"id": "Parral", "group": 1, "monto": 297022, "cantidad": 1},{"id": "Curanilahue", "group": 1, "monto": 1244742, "cantidad": 2},{"id": "Lota", "group": 1, "monto": 811701, "cantidad": 1},{"id": "Talcahuano", "group": 1, "monto": 275803, "cantidad": 1},{"id": "Llanquihue", "group": 1, "monto": 333387, "cantidad": 1},{"id": "Loncoche", "group": 1, "monto": 704508, "cantidad": 2},{"id": "Cochamó", "group": 1, "monto": 1562151, "cantidad": 3},{"id": "Concepción", "group": 1, "monto": 106809, "cantidad": 1},{"id": "Linares", "group": 1, "monto": 406849, "cantidad": 2},{"id": "Ovalle", "group": 1, "monto": 2134300, "cantidad": 4},{"id": "Maipú", "group": 1, "monto": 180492, "cantidad": 1},{"id": "Pinto", "group": 1, "monto": 1000460, "cantidad": 1},{"id": "Sagrada Familia", "group": 1, "monto": 168431, "cantidad": 1},{"id": "San Pedro de la Paz", "group": 1, "monto": 704713, "cantidad": 3},{"id": "Las Cabras", "group": 1, "monto": 3382305, "cantidad": 1},{"id": "Puerto Varas", "group": 1, "monto": 3590183, "cantidad": 3},{"id": "Arica", "group": 1, "monto": 2285637, "cantidad": 1},{"id": "Bulnes", "group": 1, "monto": 718440, "cantidad": 1},{"id": "San Nicolás", "group": 1, "monto": 96689, "cantidad": 1},{"id": "El Carmen", "group": 1, "monto": 34070, "cantidad": 2},{"id": "Penco", "group": 1, "monto": 1167952, "cantidad": 5},{"id": "Coyhaique", "group": 1, "monto": 781513, "cantidad": 1},{"id": "La Serena", "group": 1, "monto": 25701, "cantidad": 1},{"id": "Quillota", "group": 1, "monto": 103207, "cantidad": 1},{"id": "Gabriel Alexis", "group": 2, "monto": 3715248, "cantidad": 1},{"id": "Atlantik Ltda.", "group": 2, "monto": 37054, "cantidad": 1},{"id": "Metanoia", "group": 2, "monto": 443809, "cantidad": 1},{"id": "PROASAL LTDA", "group": 2, "monto": 80700, "cantidad": 1},{"id": "LIBRERIAS DON MARIO E.I.R.L.", "group": 2, "monto": 388801, "cantidad": 1},{"id": "Soc. Comercial Le Papi Cia Ltda.", "group": 2, "monto": 8695, "cantidad": 1},{"id": "alfombras dupre ltda.", "group": 2, "monto": 71827, "cantidad": 1},{"id": "Sociedad Karina Cardenas Astete y Compañia Ltda.", "group": 2, "monto": 383212, "cantidad": 1},{"id": "SIGIFREDO RIVERA PINUER", "group": 2, "monto": 740720, "cantidad": 2},{"id": "SORAYA ANICH ALLEL", "group": 2, "monto": 145006, "cantidad": 2},{"id": "ferreretia los heroes", "group": 2, "monto": 96689, "cantidad": 1},{"id": "FERRETERIAS IBERIA LTDA", "group": 2, "monto": 2285637, "cantidad": 1},{"id": "Sociedad Comercial Oficinta Ltda.", "group": 2, "monto": 1019507, "cantidad": 1},{"id": "Importadora y Comercializadora Mercado Privado SPA", "group": 2, "monto": 668550, "cantidad": 1},{"id": "Manufacturas de Alfombras Checoeslovaquia Ltda.", "group": 2, "monto": 1584212, "cantidad": 4},{"id": "Imagenes.com", "group": 2, "monto": 1611737, "cantidad": 1},{"id": "PRISA S.A.", "group": 2, "monto": 248183, "cantidad": 1},{"id": "Supermercado La Montaña", "group": 2, "monto": 268117, "cantidad": 1},{"id": "claudio gutierrez almonacid", "group": 2, "monto": 202443, "cantidad": 1},{"id": "termolam", "group": 2, "monto": 744141, "cantidad": 4},{"id": "DEPORTES SCUTTI", "group": 2, "monto": 1090172, "cantidad": 1},{"id": "Juan Fernando", "group": 2, "monto": 207076, "cantidad": 1},{"id": "Comercial Agustin Limitada", "group": 2, "monto": 297022, "cantidad": 1},{"id": "ferreteria551", "group": 2, "monto": 335162, "cantidad": 1},{"id": "FERNANDO VELOSO OLIVA", "group": 2, "monto": 342335, "cantidad": 2},{"id": "Juan Paredes", "group": 2, "monto": 385846, "cantidad": 1},{"id": "MULTICOMERCIAL CHILLAN LTDA", "group": 2, "monto": 718440, "cantidad": 1},{"id": "Redoffice", "group": 2, "monto": 1993991, "cantidad": 3},{"id": "FERRETERIA OHIGGINS", "group": 2, "monto": 331962, "cantidad": 1},{"id": "Dinse Insumos e.i.r.l.", "group": 2, "monto": 418820, "cantidad": 2},{"id": "F y F Ltda.", "group": 2, "monto": 675987, "cantidad": 1},{"id": "Comercial Sucesion Jorge Abad", "group": 2, "monto": 203339, "cantidad": 1},{"id": "SOCIEDAD COMERCIAL OCTAVA LIMITADA", "group": 2, "monto": 892135, "cantidad": 1},{"id": "wyr", "group": 2, "monto": 333387, "cantidad": 1},{"id": "Ferretería San Sebastián", "group": 2, "monto": 1000460, "cantidad": 1},{"id": "Comercial Ofimat Ltda.", "group": 2, "monto": 199165, "cantidad": 1},{"id": "Gladys del Carmen Arteaga Soto", "group": 2, "monto": 180492, "cantidad": 1},{"id": "Alfombras Winter", "group": 2, "monto": 3275437, "cantidad": 1},{"id": "COMERCIALIZADORA Y DISTRIBUIDORA DE LIBROS LIMITAD", "group": 2, "monto": 168431, "cantidad": 1},{"id": "Comercial San Cristobal", "group": 2, "monto": 1003327, "cantidad": 1},{"id": "LUSTER", "group": 2, "monto": 3193879, "cantidad": 6},{"id": "URZUA SCHWALM Y CIA LIMITADA", "group": 2, "monto": 36028, "cantidad": 1},{"id": "SUPERMERCADO COMBARBALA", "group": 2, "monto": 419976, "cantidad": 2},{"id": "MANUEL EMILIO MUÑOZ ABOCHACRA", "group": 2, "monto": 1628268, "cantidad": 1},{"id": "OPENSUR CHILE SA", "group": 2, "monto": 3737110, "cantidad": 1},{"id": "cusatto sa", "group": 2, "monto": 474851, "cantidad": 1},{"id": "El Mirador La Ligua", "group": 2, "monto": 430380, "cantidad": 1},{"id": "DIMERC S.A.", "group": 2, "monto": 25701, "cantidad": 1},{"id": "Leonardo", "group": 2, "monto": 314984, "cantidad": 1},{"id": "CLAUDIO DAVID", "group": 2, "monto": 139221, "cantidad": 1},{"id": "Ferreteria sur", "group": 2, "monto": 159704, "cantidad": 2},{"id": "Distribuidora Surmontt", "group": 2, "monto": 132074, "cantidad": 3},{"id": "MEGAOFFICE", "group": 2, "monto": 299508, "cantidad": 1},{"id": "Ferretería Lonza y Cía. Ltda.", "group": 2, "monto": 2807007, "cantidad": 4},{"id": "COMERCIAL COPELEC S.A.", "group": 2, "monto": 25375, "cantidad": 1},{"id": "Agro-Jaque Ltda.", "group": 2, "monto": 155380, "cantidad": 1},{"id": "materiales de construcción alaska", "group": 2, "monto": 647366, "cantidad": 1},{"id": "RED OFFICE SUR LTDA.", "group": 2, "monto": 255104, "cantidad": 2},{"id": "BOSCO EDUARDO", "group": 2, "monto": 606370, "cantidad": 2},{"id": "COMERCIAL HARCHA Y CIA LTDA", "group": 2, "monto": 304390, "cantidad": 2},{"id": "TROFEOS MEDAL", "group": 2, "monto": 2345102, "cantidad": 2},{"id": "CONSTRUCTORA INVERCIC LTDA", "group": 2, "monto": 1040400, "cantidad": 1},{"id": "FERRETERIAS WEITZLER S.A.", "group": 2, "monto": 2138512, "cantidad": 8},{"id": "Interfilm S.A.", "group": 2, "monto": 2948004, "cantidad": 6},{"id": "SUPERMERCADO LA MUNDIAL", "group": 2, "monto": 35958, "cantidad": 1},{"id": "SOCIEDAD COMERCIAL LA CASCADA LTDA.", "group": 2, "monto": 104378, "cantidad": 1},{"id": "C.S.C. LTDA.", "group": 2, "monto": 2630649, "cantidad": 1},{"id": "FERRINOR E.I.R.L.", "group": 2, "monto": 811701, "cantidad": 1},{"id": "Soc. Com.  Tuchie Jaduri Ltda", "group": 2, "monto": 12243, "cantidad": 1},{"id": "Decoraciones HÔGUER", "group": 2, "monto": 5635566, "cantidad": 2},{"id": "Ariel Viveros Muñoz", "group": 2, "monto": 50437, "cantidad": 1},{"id": "OPAES LTDA.", "group": 2, "monto": 188486, "cantidad": 1},{"id": "GAC Maquinas Ltda", "group": 2, "monto": 95413, "cantidad": 1},{"id": "Susana del Carmen", "group": 2, "monto": 205564, "cantidad": 2},{"id": "CIENPIES", "group": 2, "monto": 593424, "cantidad": 1},{"id": "María", "group": 2, "monto": 705025, "cantidad": 1},{"id": "COMERCIAL SOCOEPA SOCIEDAD ANONIMA", "group": 2, "monto": 135931, "cantidad": 1},{"id": "Ramón Ubilla Oviedo", "group": 2, "monto": 181528, "cantidad": 1},{"id": "Mundo Muebles E.I.R.L", "group": 2, "monto": 1378135, "cantidad": 5},{"id": "MONICA ALICIA", "group": 2, "monto": 2849463, "cantidad": 1},{"id": "COMERCIAL DOS CUMBRES", "group": 2, "monto": 781513, "cantidad": 1},{"id": "Ferreteria Santo Domingo", "group": 2, "monto": 536100, "cantidad": 1},{"id": "SODIMAC S.A. - CONVENIOS MARCO", "group": 2, "monto": 1103452, "cantidad": 8},{"id": "Benito Nicolas Marsan Lagunas", "group": 2, "monto": 241629, "cantidad": 3},{"id": "ELSA BELTRAN ROCHA Y CIA. LTDA.", "group": 2, "monto": 227811, "cantidad": 1},{"id": "LA BODEGA", "group": 2, "monto": 100992, "cantidad": 1},{"id": "SOLFLEX", "group": 2, "monto": 597308, "cantidad": 1},{"id": "COLCHONESSUR", "group": 2, "monto": 291597, "cantidad": 1},{"id": "COMERCIAL SAN CRISTOBAL SPA.", "group": 2, "monto": 3382305, "cantidad": 1},{"id": "solucenter", "group": 2, "monto": 21267, "cantidad": 1},{"id": "Abel  Segundo", "group": 2, "monto": 6703959, "cantidad": 11},{"id": "Redoffice XII", "group": 2, "monto": 187324, "cantidad": 1},{"id": "SOCIEDAD COMERCIAL MATUS BELMAR LTDA.", "group": 2, "monto": 280298, "cantidad": 1}],"links": [{"source": "Soc. Com.  Tuchie Jaduri Ltda", "target": "Paillaco", "monto": 12243, "cantidad": 1},{"source": "Comercial Agustin Limitada", "target": "Parral", "monto": 297022, "cantidad": 1},{"source": "LUSTER", "target": "Lebu", "monto": 276303, "cantidad": 1},{"source": "Ramón Ubilla Oviedo", "target": "Puerto Montt", "monto": 181528, "cantidad": 1},{"source": "Redoffice", "target": "San Esteban", "monto": 303821, "cantidad": 1},{"source": "termolam", "target": "Linares", "monto": 207684, "cantidad": 1},{"source": "María", "target": "Cochamó", "monto": 705025, "cantidad": 1},{"source": "COMERCIAL COPELEC S.A.", "target": "El Carmen", "monto": 25375, "cantidad": 1},{"source": "Manufacturas de Alfombras Checoeslovaquia Ltda.", "target": "Pichidegua", "monto": 502905, "cantidad": 3},{"source": "MONICA ALICIA", "target": "Puerto Varas", "monto": 2849463, "cantidad": 1},{"source": "claudio gutierrez almonacid", "target": "Hualaihue", "monto": 202443, "cantidad": 1},{"source": "SODIMAC S.A. - CONVENIOS MARCO", "target": "San Pedro de la Paz", "monto": 59111, "cantidad": 1},{"source": "SOCIEDAD COMERCIAL OCTAVA LIMITADA", "target": "Los Ángeles", "monto": 892135, "cantidad": 1},{"source": "LUSTER", "target": "Valdivia", "monto": 1473340, "cantidad": 2},{"source": "Abel  Segundo", "target": "Mulchén", "monto": 1076613, "cantidad": 1},{"source": "COLCHONESSUR", "target": "Victoria", "monto": 291597, "cantidad": 1},{"source": "FERRETERIAS WEITZLER S.A.", "target": "Los Muermos", "monto": 70511, "cantidad": 1},{"source": "El Mirador La Ligua", "target": "La Ligua", "monto": 430380, "cantidad": 1},{"source": "Mundo Muebles E.I.R.L", "target": "Valdivia", "monto": 286170, "cantidad": 1},{"source": "COMERCIAL SAN CRISTOBAL SPA.", "target": "Las Cabras", "monto": 3382305, "cantidad": 1},{"source": "COMERCIAL HARCHA Y CIA LTDA", "target": "Los Lagos", "monto": 304390, "cantidad": 2},{"source": "Ferreteria sur", "target": "Chile Chico", "monto": 159704, "cantidad": 2},{"source": "DIMERC S.A.", "target": "La Serena", "monto": 25701, "cantidad": 1},{"source": "Distribuidora Surmontt", "target": "Puerto Montt", "monto": 105790, "cantidad": 2},{"source": "ferreteria551", "target": "Nacimiento", "monto": 335162, "cantidad": 1},{"source": "Redoffice", "target": "Los Ángeles", "monto": 1567510, "cantidad": 1},{"source": "Susana del Carmen", "target": "La Cisterna", "monto": 205564, "cantidad": 2},{"source": "Abel  Segundo", "target": "Los Ángeles", "monto": 437394, "cantidad": 2},{"source": "SODIMAC S.A. - CONVENIOS MARCO", "target": "San Rafael", "monto": 451089, "cantidad": 3},{"source": "Decoraciones HÔGUER", "target": "Temuco", "monto": 5635566, "cantidad": 2},{"source": "Abel  Segundo", "target": "San Pedro de la Paz", "monto": 645602, "cantidad": 2},{"source": "Ferretería Lonza y Cía. Ltda.", "target": "Vallenar", "monto": 2807007, "cantidad": 4},{"source": "CIENPIES", "target": "Carahue", "monto": 593424, "cantidad": 1},{"source": "Redoffice XII", "target": "San Gregorio", "monto": 187324, "cantidad": 1},{"source": "Abel  Segundo", "target": "Providencia", "monto": 1950000, "cantidad": 1},{"source": "Importadora y Comercializadora Mercado Privado SPA", "target": "Loncoche", "monto": 668550, "cantidad": 1},{"source": "COMERCIAL SOCOEPA SOCIEDAD ANONIMA", "target": "Paillaco", "monto": 135931, "cantidad": 1},{"source": "Interfilm S.A.", "target": "Los Ángeles", "monto": 1714913, "cantidad": 1},{"source": "LUSTER", "target": "Curanilahue", "monto": 1008244, "cantidad": 1},{"source": "Mundo Muebles E.I.R.L", "target": "Puerto Montt", "monto": 520984, "cantidad": 1},{"source": "Manufacturas de Alfombras Checoeslovaquia Ltda.", "target": "Chillán", "monto": 1081307, "cantidad": 1},{"source": "Abel  Segundo", "target": "Chillán", "monto": 76111, "cantidad": 1},{"source": "OPAES LTDA.", "target": "Hualqui", "monto": 188486, "cantidad": 1},{"source": "Sociedad Comercial Oficinta Ltda.", "target": "Arauco", "monto": 1019507, "cantidad": 1},{"source": "Interfilm S.A.", "target": "Penco", "monto": 698772, "cantidad": 2},{"source": "Redoffice", "target": "Nacimiento", "monto": 122660, "cantidad": 1},{"source": "FERRETERIAS WEITZLER S.A.", "target": "San Pablo", "monto": 235154, "cantidad": 1},{"source": "GAC Maquinas Ltda", "target": "Puerto Octay", "monto": 95413, "cantidad": 1},{"source": "SOCIEDAD COMERCIAL LA CASCADA LTDA.", "target": "Aysén", "monto": 104378, "cantidad": 1},{"source": "Abel  Segundo", "target": "Lebu", "monto": 358555, "cantidad": 1},{"source": "Ariel Viveros Muñoz", "target": "Traiguén", "monto": 50437, "cantidad": 1},{"source": "F y F Ltda.", "target": "La Ligua", "monto": 675987, "cantidad": 1},{"source": "Agro-Jaque Ltda.", "target": "Colbún", "monto": 155380, "cantidad": 1},{"source": "SODIMAC S.A. - CONVENIOS MARCO", "target": "Nacimiento", "monto": 124072, "cantidad": 1},{"source": "FERRINOR E.I.R.L.", "target": "Lota", "monto": 811701, "cantidad": 1},{"source": "DEPORTES SCUTTI", "target": "La Ligua", "monto": 1090172, "cantidad": 1},{"source": "FERNANDO VELOSO OLIVA", "target": "Quillón", "monto": 116038, "cantidad": 1},{"source": "Sociedad Karina Cardenas Astete y Compañia Ltda.", "target": "Futaleufú", "monto": 383212, "cantidad": 1},{"source": "FERRETERIAS WEITZLER S.A.", "target": "Hualaihue", "monto": 338648, "cantidad": 1},{"source": "URZUA SCHWALM Y CIA LIMITADA", "target": "Lago Ranco", "monto": 36028, "cantidad": 1},{"source": "TROFEOS MEDAL", "target": "Hualaihue", "monto": 2345102, "cantidad": 2},{"source": "C.S.C. LTDA.", "target": "Calama", "monto": 2630649, "cantidad": 1},{"source": "Benito Nicolas Marsan Lagunas", "target": "San Gregorio", "monto": 241629, "cantidad": 3},{"source": "FERRETERIAS IBERIA LTDA", "target": "Arica", "monto": 2285637, "cantidad": 1},{"source": "FERRETERIAS WEITZLER S.A.", "target": "Fresia", "monto": 259066, "cantidad": 1},{"source": "Gladys del Carmen Arteaga Soto", "target": "Maipú", "monto": 180492, "cantidad": 1},{"source": "COMERCIAL DOS CUMBRES", "target": "Coyhaique", "monto": 781513, "cantidad": 1},{"source": "SORAYA ANICH ALLEL", "target": "Ovalle", "monto": 145006, "cantidad": 2},{"source": "Interfilm S.A.", "target": "Lo Barnechea", "monto": 324834, "cantidad": 2},{"source": "Supermercado La Montaña", "target": "San Fabián", "monto": 268117, "cantidad": 1},{"source": "Alfombras Winter", "target": "Chanco", "monto": 3275437, "cantidad": 1},{"source": "FERRETERIAS WEITZLER S.A.", "target": "Puerto Montt", "monto": 33770, "cantidad": 1},{"source": "solucenter", "target": "Los Álamos", "monto": 21267, "cantidad": 1},{"source": "Comercial Sucesion Jorge Abad", "target": "Lumaco", "monto": 203339, "cantidad": 1},{"source": "SOCIEDAD COMERCIAL MATUS BELMAR LTDA.", "target": "Cauquenes", "monto": 280298, "cantidad": 1},{"source": "PROASAL LTDA", "target": "Vilcún", "monto": 80700, "cantidad": 1},{"source": "LUSTER", "target": "Coltauco", "monto": 435992, "cantidad": 2},{"source": "Distribuidora Surmontt", "target": "La Unión", "monto": 26284, "cantidad": 1},{"source": "OPENSUR CHILE SA", "target": "Valdivia", "monto": 3737110, "cantidad": 1},{"source": "Imagenes.com", "target": "Coronel", "monto": 1611737, "cantidad": 1},{"source": "RED OFFICE SUR LTDA.", "target": "Pitrufquén", "monto": 204629, "cantidad": 1},{"source": "CLAUDIO DAVID", "target": "Quinchao", "monto": 139221, "cantidad": 1},{"source": "Atlantik Ltda.", "target": "Pitrufquén", "monto": 37054, "cantidad": 1},{"source": "MEGAOFFICE", "target": "Arauco", "monto": 299508, "cantidad": 1},{"source": "Mundo Muebles E.I.R.L", "target": "Osorno", "monto": 334483, "cantidad": 2},{"source": "Abel  Segundo", "target": "Nacimiento", "monto": 170390, "cantidad": 1},{"source": "Ferreteria Santo Domingo", "target": "Florida", "monto": 536100, "cantidad": 1},{"source": "FERRETERIA OHIGGINS", "target": "Diego de Almagro", "monto": 331962, "cantidad": 1},{"source": "LIBRERIAS DON MARIO E.I.R.L.", "target": "Cauquenes", "monto": 388801, "cantidad": 1},{"source": "COMERCIALIZADORA Y DISTRIBUIDORA DE LIBROS LIMITAD", "target": "Sagrada Familia", "monto": 168431, "cantidad": 1},{"source": "Dinse Insumos e.i.r.l.", "target": "Colchane", "monto": 418820, "cantidad": 2},{"source": "SUPERMERCADO COMBARBALA", "target": "Combarbalá", "monto": 419976, "cantidad": 2},{"source": "LA BODEGA", "target": "Victoria", "monto": 100992, "cantidad": 1},{"source": "SUPERMERCADO LA MUNDIAL", "target": "Loncoche", "monto": 35958, "cantidad": 1},{"source": "FERRETERIAS WEITZLER S.A.", "target": "Cochamó", "monto": 857126, "cantidad": 2},{"source": "Juan Fernando", "target": "Tucapel", "monto": 207076, "cantidad": 1},{"source": "SOLFLEX", "target": "San Rosendo", "monto": 597308, "cantidad": 1},{"source": "BOSCO EDUARDO", "target": "Talcahuano", "monto": 275803, "cantidad": 1},{"source": "alfombras dupre ltda.", "target": "Puerto Montt", "monto": 71827, "cantidad": 1},{"source": "MULTICOMERCIAL CHILLAN LTDA", "target": "Bulnes", "monto": 718440, "cantidad": 1},{"source": "PRISA S.A.", "target": "La Cisterna", "monto": 248183, "cantidad": 1},{"source": "ELSA BELTRAN ROCHA Y CIA. LTDA.", "target": "Lumaco", "monto": 227811, "cantidad": 1},{"source": "Ferretería San Sebastián", "target": "Pinto", "monto": 1000460, "cantidad": 1},{"source": "CONSTRUCTORA INVERCIC LTDA", "target": "Chillán Viejo", "monto": 1040400, "cantidad": 1},{"source": "Metanoia", "target": "Huechuraba", "monto": 443809, "cantidad": 1},{"source": "Abel  Segundo", "target": "Ovalle", "monto": 1989294, "cantidad": 2},{"source": "ferreretia los heroes", "target": "San Nicolás", "monto": 96689, "cantidad": 1},{"source": "Comercial San Cristobal", "target": "San Fabián", "monto": 1003327, "cantidad": 1},{"source": "SIGIFREDO RIVERA PINUER", "target": "Puerto Varas", "monto": 740720, "cantidad": 2},{"source": "SODIMAC S.A. - CONVENIOS MARCO", "target": "Penco", "monto": 469180, "cantidad": 3},{"source": "termolam", "target": "La Unión", "monto": 326441, "cantidad": 1},{"source": "cusatto sa", "target": "Temuco", "monto": 474851, "cantidad": 1},{"source": "Mundo Muebles E.I.R.L", "target": "Curanilahue", "monto": 236498, "cantidad": 1},{"source": "FERNANDO VELOSO OLIVA", "target": "Arauco", "monto": 226297, "cantidad": 1},{"source": "materiales de construcción alaska", "target": "Lonquimay", "monto": 647366, "cantidad": 1},{"source": "Leonardo", "target": "Palena", "monto": 314984, "cantidad": 1},{"source": "termolam", "target": "Concepción", "monto": 106809, "cantidad": 1},{"source": "Comercial Ofimat Ltda.", "target": "Linares", "monto": 199165, "cantidad": 1},{"source": "Juan Paredes", "target": "Lonquimay", "monto": 385846, "cantidad": 1},{"source": "BOSCO EDUARDO", "target": "Lebu", "monto": 330567, "cantidad": 1},{"source": "Interfilm S.A.", "target": "Río Claro", "monto": 209485, "cantidad": 1},{"source": "MANUEL EMILIO MUÑOZ ABOCHACRA", "target": "La Ligua", "monto": 1628268, "cantidad": 1},{"source": "FERRETERIAS WEITZLER S.A.", "target": "Frutillar", "monto": 344237, "cantidad": 1},{"source": "Soc. Comercial Le Papi Cia Ltda.", "target": "El Carmen", "monto": 8695, "cantidad": 1},{"source": "wyr", "target": "Llanquihue", "monto": 333387, "cantidad": 1},{"source": "RED OFFICE SUR LTDA.", "target": "Valdivia", "monto": 50475, "cantidad": 1},{"source": "Gabriel Alexis", "target": "Los Ángeles", "monto": 3715248, "cantidad": 1},{"source": "termolam", "target": "Quillota", "monto": 103207, "cantidad": 1}]	} ] }