{"Servicios_de_brocas_de_barrena_para_yacimientos_petrolíferos": [ {"nodes": [{"id": "Mulchén", "group": 1, "monto": 319826, "cantidad": 2},{"id": "Nueva Imperial", "group": 1, "monto": 189468, "cantidad": 1},{"id": "Chiguayante", "group": 1, "monto": 401963, "cantidad": 1},{"id": "Lonquimay", "group": 1, "monto": 99288, "cantidad": 1},{"id": "Santa María", "group": 1, "monto": 230060, "cantidad": 1},{"id": "Petorca", "group": 1, "monto": 1073538, "cantidad": 1},{"id": "La Ligua", "group": 1, "monto": 354522, "cantidad": 1},{"id": "San Fernando", "group": 1, "monto": 442310, "cantidad": 1},{"id": "Longaví", "group": 1, "monto": 34023, "cantidad": 1},{"id": "Pozo al Monte", "group": 1, "monto": 406843, "cantidad": 1},{"id": "Salamanca", "group": 1, "monto": 116806, "cantidad": 1},{"id": "Llanquihue", "group": 1, "monto": 73862, "cantidad": 1},{"id": "Victoria", "group": 1, "monto": 619981, "cantidad": 4},{"id": "Villa Alemana", "group": 1, "monto": 533586, "cantidad": 1},{"id": "Paillaco", "group": 1, "monto": 1026033, "cantidad": 2},{"id": "Lautaro", "group": 1, "monto": 4206143, "cantidad": 4},{"id": "Hijuelas", "group": 1, "monto": 93785, "cantidad": 1},{"id": "Las Cabras", "group": 1, "monto": 46386, "cantidad": 1},{"id": "El Carmen", "group": 1, "monto": 151034, "cantidad": 1},{"id": "Tirúa", "group": 1, "monto": 540553, "cantidad": 1},{"id": "Mariquina", "group": 1, "monto": 410052, "cantidad": 4},{"id": "El Mirador La Ligua", "group": 2, "monto": 354522, "cantidad": 1},{"id": "wyr", "group": 2, "monto": 73862, "cantidad": 1},{"id": "José Alejandro", "group": 2, "monto": 406843, "cantidad": 1},{"id": "O Y P COMERCIAL LTDA.", "group": 2, "monto": 533586, "cantidad": 1},{"id": "AGRASAN", "group": 2, "monto": 230060, "cantidad": 1},{"id": "CARLOS BADILLA ROCHA", "group": 2, "monto": 319826, "cantidad": 2},{"id": "VILMA", "group": 2, "monto": 1073538, "cantidad": 1},{"id": "Comercial Eduardo Pradenas Avendaño E.I.R.L.", "group": 2, "monto": 401963, "cantidad": 1},{"id": "uberlinda elizabeth", "group": 2, "monto": 957960, "cantidad": 1},{"id": "ferreteriaramirez", "group": 2, "monto": 225758, "cantidad": 3},{"id": "Sociedad Ferretera Esmeralda Limitada", "group": 2, "monto": 46386, "cantidad": 1},{"id": "RENATO DIAZ S.A.", "group": 2, "monto": 151034, "cantidad": 1},{"id": "Antonio Salvador Cereijo Aguad", "group": 2, "monto": 116806, "cantidad": 1},{"id": "Ferreteria Casa Garcia", "group": 2, "monto": 442310, "cantidad": 1},{"id": "santos hnos ltda", "group": 2, "monto": 540553, "cantidad": 1},{"id": "Agrocomercial Valle Lonquimay", "group": 2, "monto": 99288, "cantidad": 1},{"id": "Narabia Yusabia", "group": 2, "monto": 34023, "cantidad": 1},{"id": "Frindt S.A.", "group": 2, "monto": 189468, "cantidad": 1},{"id": "franjamar", "group": 2, "monto": 184294, "cantidad": 1},{"id": "Ferreteria Allipen ltda.", "group": 2, "monto": 619981, "cantidad": 4},{"id": "INELCO LIMITADA", "group": 2, "monto": 68073, "cantidad": 1},{"id": "RyT Ltda", "group": 2, "monto": 93785, "cantidad": 1},{"id": "Ferretería El Rodeo", "group": 2, "monto": 4206143, "cantidad": 4}],"links": [{"source": "Comercial Eduardo Pradenas Avendaño E.I.R.L.", "target": "Chiguayante", "monto": 401963, "cantidad": 1},{"source": "wyr", "target": "Llanquihue", "monto": 73862, "cantidad": 1},{"source": "ferreteriaramirez", "target": "Mariquina", "monto": 225758, "cantidad": 3},{"source": "Ferreteria Casa Garcia", "target": "San Fernando", "monto": 442310, "cantidad": 1},{"source": "Antonio Salvador Cereijo Aguad", "target": "Salamanca", "monto": 116806, "cantidad": 1},{"source": "José Alejandro", "target": "Pozo al Monte", "monto": 406843, "cantidad": 1},{"source": "franjamar", "target": "Mariquina", "monto": 184294, "cantidad": 1},{"source": "O Y P COMERCIAL LTDA.", "target": "Villa Alemana", "monto": 533586, "cantidad": 1},{"source": "Frindt S.A.", "target": "Nueva Imperial", "monto": 189468, "cantidad": 1},{"source": "Ferreteria Allipen ltda.", "target": "Victoria", "monto": 619981, "cantidad": 4},{"source": "AGRASAN", "target": "Santa María", "monto": 230060, "cantidad": 1},{"source": "CARLOS BADILLA ROCHA", "target": "Mulchén", "monto": 319826, "cantidad": 2},{"source": "INELCO LIMITADA", "target": "Paillaco", "monto": 68073, "cantidad": 1},{"source": "santos hnos ltda", "target": "Tirúa", "monto": 540553, "cantidad": 1},{"source": "RENATO DIAZ S.A.", "target": "El Carmen", "monto": 151034, "cantidad": 1},{"source": "El Mirador La Ligua", "target": "La Ligua", "monto": 354522, "cantidad": 1},{"source": "Ferretería El Rodeo", "target": "Lautaro", "monto": 4206143, "cantidad": 4},{"source": "RyT Ltda", "target": "Hijuelas", "monto": 93785, "cantidad": 1},{"source": "Sociedad Ferretera Esmeralda Limitada", "target": "Las Cabras", "monto": 46386, "cantidad": 1},{"source": "uberlinda elizabeth", "target": "Paillaco", "monto": 957960, "cantidad": 1},{"source": "Agrocomercial Valle Lonquimay", "target": "Lonquimay", "monto": 99288, "cantidad": 1},{"source": "VILMA", "target": "Petorca", "monto": 1073538, "cantidad": 1},{"source": "Narabia Yusabia", "target": "Longaví", "monto": 34023, "cantidad": 1}]	} ] }